{"path":"E:\\Yangdingming\\Documents\\output-images3\\air-hole4(hollow-bead)-095.jpg","outputs":{"object":[{"name":"air-hole","bndbox":{"xmin":181,"ymin":342,"xmax":196,"ymax":355}},{"name":"air-hole","bndbox":{"xmin":237,"ymin":393,"xmax":252,"ymax":407}},{"name":"air-hole","bndbox":{"xmin":316,"ymin":467,"xmax":332,"ymax":480}},{"name":"air-hole","bndbox":{"xmin":333,"ymin":482,"xmax":351,"ymax":497}},{"name":"air-hole","bndbox":{"xmin":401,"ymin":547,"xmax":416,"ymax":560}},{"name":"air-hole","bndbox":{"xmin":666,"ymin":803,"xmax":687,"ymax":817}},{"name":"hollow-bead","bndbox":{"xmin":601,"ymin":743,"xmax":659,"ymax":790}}]},"time_labeled":1614771919842,"labeled":true,"size":{"width":1182,"height":820,"depth":3}}