{"path":"E:\\Yangdingming\\Documents\\output-images3\\air-hole4(hollow-bead)-194.jpg","outputs":{"object":[{"name":"air-hole","bndbox":{"xmin":891,"ymin":767,"xmax":908,"ymax":780}},{"name":"air-hole","bndbox":{"xmin":586,"ymin":492,"xmax":606,"ymax":505}},{"name":"air-hole","bndbox":{"xmin":263,"ymin":197,"xmax":283,"ymax":212}},{"name":"hollow-bead","bndbox":{"xmin":200,"ymin":136,"xmax":257,"ymax":181}}]},"time_labeled":1614778568700,"labeled":true,"size":{"width":1182,"height":820,"depth":3}}