{"path":"E:\\Yangdingming\\Documents\\output-images3\\air-hole4(hollow-bead)-155.jpg","outputs":{"object":[{"name":"hollow-bead","bndbox":{"xmin":347,"ymin":425,"xmax":406,"ymax":467}},{"name":"air-hole","bndbox":{"xmin":736,"ymin":775,"xmax":756,"ymax":792}},{"name":"air-hole","bndbox":{"xmin":411,"ymin":482,"xmax":431,"ymax":497}},{"name":"air-hole","bndbox":{"xmin":82,"ymin":163,"xmax":96,"ymax":177}},{"name":"air-hole","bndbox":{"xmin":61,"ymin":145,"xmax":77,"ymax":158}},{"name":"air-hole","bndbox":{"xmin":147,"ymin":227,"xmax":162,"ymax":240}}]},"time_labeled":1614776223982,"labeled":true,"size":{"width":1182,"height":820,"depth":3}}