{"path":"E:\\Yangdingming\\Documents\\output-images3\\air-hole4(hollow-bead)-160.jpg","outputs":{"object":[{"name":"air-hole","bndbox":{"xmin":29,"ymin":102,"xmax":43,"ymax":114}},{"name":"air-hole","bndbox":{"xmin":47,"ymin":117,"xmax":64,"ymax":132}},{"name":"air-hole","bndbox":{"xmin":116,"ymin":182,"xmax":131,"ymax":195}},{"name":"air-hole","bndbox":{"xmin":381,"ymin":437,"xmax":401,"ymax":453}},{"name":"air-hole","bndbox":{"xmin":706,"ymin":732,"xmax":726,"ymax":747}},{"name":"hollow-bead","bndbox":{"xmin":317,"ymin":378,"xmax":381,"ymax":425}}]},"time_labeled":1614776495319,"labeled":true,"size":{"width":1182,"height":820,"depth":3}}