{"path":"E:\\Yangdingming\\Documents\\output-images3\\air-hole4(hollow-bead)-175.jpg","outputs":{"object":[{"name":"hollow-bead","bndbox":{"xmin":296,"ymin":272,"xmax":354,"ymax":318}},{"name":"air-hole","bndbox":{"xmin":684,"ymin":625,"xmax":702,"ymax":642}},{"name":"air-hole","bndbox":{"xmin":361,"ymin":332,"xmax":379,"ymax":348}},{"name":"air-hole","bndbox":{"xmin":94,"ymin":75,"xmax":109,"ymax":90}},{"name":"air-hole","bndbox":{"xmin":24,"ymin":12,"xmax":42,"ymax":27}}]},"time_labeled":1614777937348,"labeled":true,"size":{"width":1182,"height":820,"depth":3}}