{"path":"E:\\Yangdingming\\Documents\\output-images3\\air-hole4(hollow-bead)-081.jpg","outputs":{"object":[{"name":"air-hole","bndbox":{"xmin":552,"ymin":615,"xmax":569,"ymax":628}},{"name":"air-hole","bndbox":{"xmin":482,"ymin":552,"xmax":501,"ymax":564}},{"name":"air-hole","bndbox":{"xmin":466,"ymin":533,"xmax":481,"ymax":547}},{"name":"air-hole","bndbox":{"xmin":386,"ymin":462,"xmax":403,"ymax":474}},{"name":"air-hole","bndbox":{"xmin":331,"ymin":408,"xmax":347,"ymax":422}}]},"time_labeled":1614770473045,"labeled":true,"size":{"width":1182,"height":820,"depth":3}}