{"path":"E:\\Yangdingming\\Documents\\output-images3\\air-hole4(hollow-bead)-063.jpg","outputs":{"object":[{"name":"air-hole","bndbox":{"xmin":681,"ymin":705,"xmax":694,"ymax":717}},{"name":"air-hole","bndbox":{"xmin":611,"ymin":642,"xmax":627,"ymax":655}},{"name":"air-hole","bndbox":{"xmin":592,"ymin":625,"xmax":607,"ymax":637}},{"name":"air-hole","bndbox":{"xmin":456,"ymin":500,"xmax":471,"ymax":512}},{"name":"air-hole","bndbox":{"xmin":514,"ymin":552,"xmax":527,"ymax":565}}]},"time_labeled":1614762444157,"labeled":true,"size":{"width":1182,"height":820,"depth":3}}