{"path":"E:\\Yangdingming\\Documents\\output-images3\\air-hole4(hollow-bead)-191.jpg","outputs":{"object":[{"name":"hollow-bead","bndbox":{"xmin":231,"ymin":157,"xmax":287,"ymax":202}},{"name":"air-hole","bndbox":{"xmin":291,"ymin":215,"xmax":312,"ymax":233}},{"name":"air-hole","bndbox":{"xmin":616,"ymin":510,"xmax":636,"ymax":527}},{"name":"air-hole","bndbox":{"xmin":921,"ymin":785,"xmax":939,"ymax":800}}]},"time_labeled":1614778463083,"labeled":true,"size":{"width":1182,"height":820,"depth":3}}