{"path":"E:\\Yangdingming\\Documents\\output-images3\\air-hole3-57.jpg","outputs":{"object":[{"name":"air-hole","bndbox":{"xmin":351,"ymin":54,"xmax":366,"ymax":68}},{"name":"air-hole","bndbox":{"xmin":399,"ymin":100,"xmax":413,"ymax":114}},{"name":"air-hole","bndbox":{"xmin":575,"ymin":259,"xmax":592,"ymax":278}},{"name":"air-hole","bndbox":{"xmin":555,"ymin":242,"xmax":571,"ymax":258}},{"name":"air-hole","bndbox":{"xmin":667,"ymin":346,"xmax":683,"ymax":360}},{"name":"air-hole","bndbox":{"xmin":719,"ymin":392,"xmax":736,"ymax":406}}]},"time_labeled":1614756210657,"labeled":true,"size":{"width":958,"height":665,"depth":3}}