{"path":"E:\\Yangdingming\\Documents\\output-images3\\air-hole5-042.jpg","outputs":{"object":[{"name":"air-hole","bndbox":{"xmin":577,"ymin":346,"xmax":592,"ymax":360}},{"name":"air-hole","bndbox":{"xmin":613,"ymin":381,"xmax":626,"ymax":393}},{"name":"air-hole","bndbox":{"xmin":651,"ymin":411,"xmax":666,"ymax":426}},{"name":"air-hole","bndbox":{"xmin":677,"ymin":436,"xmax":694,"ymax":450}},{"name":"air-hole","bndbox":{"xmin":711,"ymin":460,"xmax":729,"ymax":475}},{"name":"air-hole","bndbox":{"xmin":771,"ymin":520,"xmax":789,"ymax":535}},{"name":"air-hole","bndbox":{"xmin":800,"ymin":541,"xmax":816,"ymax":553}},{"name":"air-hole","bndbox":{"xmin":821,"ymin":560,"xmax":836,"ymax":571}},{"name":"air-hole","bndbox":{"xmin":826,"ymin":573,"xmax":845,"ymax":588}},{"name":"air-hole","bndbox":{"xmin":882,"ymin":607,"xmax":897,"ymax":620}},{"name":"air-hole","bndbox":{"xmin":906,"ymin":616,"xmax":924,"ymax":630}},{"name":"air-hole","bndbox":{"xmin":961,"ymin":670,"xmax":976,"ymax":682}},{"name":"air-hole","bndbox":{"xmin":941,"ymin":635,"xmax":961,"ymax":650}},{"name":"air-hole","bndbox":{"xmin":962,"ymin":650,"xmax":981,"ymax":663}},{"name":"air-hole","bndbox":{"xmin":988,"ymin":733,"xmax":1002,"ymax":745}},{"name":"air-hole","bndbox":{"xmin":1001,"ymin":735,"xmax":1016,"ymax":746}},{"name":"air-hole","bndbox":{"xmin":1081,"ymin":803,"xmax":1099,"ymax":815}},{"name":"air-hole","bndbox":{"xmin":1091,"ymin":780,"xmax":1107,"ymax":791}},{"name":"air-hole","bndbox":{"xmin":1106,"ymin":790,"xmax":1119,"ymax":800}},{"name":"air-hole","bndbox":{"xmin":1026,"ymin":711,"xmax":1042,"ymax":726}},{"name":"air-hole","bndbox":{"xmin":1021,"ymin":750,"xmax":1041,"ymax":763}},{"name":"air-hole","bndbox":{"xmin":1044,"ymin":733,"xmax":1061,"ymax":750}},{"name":"porosity","bndbox":{"xmin":769,"ymin":518,"xmax":1122,"ymax":815}}]},"time_labeled":1614863154401,"labeled":true,"size":{"width":1182,"height":817,"depth":3}}